satharmony/__init__.py
satharmony/emulators/__init__.py
satharmony/emulators/s2_to_mss/__init__.py
satharmony/emulators/s2_to_mss/config.py
satharmony/emulators/s2_to_mss/degradations/__init__.py
satharmony/emulators/s2_to_mss/degradations/memory_effect.py
satharmony/emulators/s2_to_mss/degradations/noise.py
satharmony/emulators/s2_to_mss/degradations/radiometric.py
satharmony/emulators/s2_to_mss/degradations/scan_artifacts.py
satharmony/emulators/s2_to_mss/degradations/spatial.py
satharmony/emulators/s2_to_mss/degradations/spectral.py
satharmony/emulators/s2_to_mss/degradations/striping.py
satharmony/emulators/s2_to_mss/functional.py
satharmony/emulators/s2_to_mss/labels.py
satharmony/emulators/s2_to_mss/pipeline.py
satharmony-0.1.5.dist-info/METADATA
satharmony-0.1.5.dist-info/WHEEL
satharmony-0.1.5.dist-info/RECORD
