Metadata-Version: 2.1
Name: satharmony
Version: 0.1.5
Summary: Sensor emulation and harmonization for Earth Observation (Sentinel-2 → Landsat MSS).
Home-page: https://github.com/IPL-UV/satharmony
License: MIT
Keywords: remote-sensing,satellite,emulation,harmonization,sentinel-2,landsat,mss,earth-observation,deep-learning
Author: Julio Contreras
Author-email: contrerasnetk@gmail.com
Requires-Python: >=3.10,<4.0
Classifier: Development Status :: 4 - Beta
Classifier: Intended Audience :: Science/Research
Classifier: License :: OSI Approved :: MIT License
Classifier: Programming Language :: Python :: 3
Classifier: Programming Language :: Python :: 3.10
Classifier: Programming Language :: Python :: 3.11
Classifier: Programming Language :: Python :: 3.12
Classifier: Programming Language :: Python :: 3 :: Only
Classifier: Topic :: Scientific/Engineering :: Artificial Intelligence
Classifier: Topic :: Scientific/Engineering :: GIS
Classifier: Topic :: Scientific/Engineering :: Image Processing
Provides-Extra: io
Requires-Dist: numpy (>=1.24.0)
Requires-Dist: pydantic (>=2.0.0)
Requires-Dist: scipy (>=1.10.0)
Project-URL: Documentation, https://github.com/IPL-UV/satharmony
Project-URL: Repository, https://github.com/IPL-UV/satharmony
